boxline/__init__.py
boxline/auth/__init__.py
boxline/auth/auth.py
boxline/memorandum/__init__.py
boxline/memorandum/api.py
boxline/memorandum/grpc.py
boxline/shift/__init__.py
boxline/shift/api.py
boxline/shift/grpc.py
boxline/user/__init__.py
boxline/user/api.py
boxline/user/grpc.py
boxline-0.1.1.dist-info/METADATA
boxline-0.1.1.dist-info/WHEEL
boxline-0.1.1.dist-info/top_level.txt
boxline-0.1.1.dist-info/RECORD
