Metadata-Version: 2.1
Name: boxline
Version: 0.1.1
Summary: sdk to connect with connecta
Home-page: https://github.com/fuf-herNef/boxline-pdk.git
Author: inndico
License: MIT
